stack_to_chunk/__init__.py
stack_to_chunk/_array_helpers.py
stack_to_chunk/_version.py
stack_to_chunk/main.py
stack_to_chunk/ome_ngff.py
stack_to_chunk/tests/test_main.py
stack_to_chunk-1.6.dist-info/LICENCE.md
stack_to_chunk-1.6.dist-info/METADATA
stack_to_chunk-1.6.dist-info/WHEEL
stack_to_chunk-1.6.dist-info/top_level.txt
stack_to_chunk-1.6.dist-info/RECORD
