Metadata-Version: 2.2
Name: stack_to_chunk
Version: 1.6
Summary: Convert stacks of images to chunked datasets
Author-email: HiP-CT Project <d.stansby@ucl.ac.uk>
License: Copyright (c) 2023, HiP-CT Project
Project-URL: homepage, https://github.com/HiPCTProject/stack-to-chunk
Classifier: Operating System :: POSIX
Classifier: Programming Language :: Python :: 3
Classifier: Programming Language :: Python :: 3 :: Only
Classifier: Programming Language :: Python :: 3.11
Classifier: Typing :: Typed
Requires-Python: >=3.11
License-File: LICENCE.md
Requires-Dist: dask==2025.2.0
Requires-Dist: joblib==1.4.2
Requires-Dist: loguru==0.7.3
Requires-Dist: numpy==2.2.3
Requires-Dist: scikit-image==0.25.1
Requires-Dist: zarr==2.18.4
Provides-Extra: dev
Requires-Dist: pre-commit; extra == "dev"
Requires-Dist: tox>=4; extra == "dev"
Provides-Extra: docs
Requires-Dist: dask-image; extra == "docs"
Requires-Dist: matplotlib; extra == "docs"
Requires-Dist: pydata-sphinx-theme; extra == "docs"
Requires-Dist: sphinx; extra == "docs"
Requires-Dist: sphinx-autoapi; extra == "docs"
Requires-Dist: sphinx-gallery; extra == "docs"
Requires-Dist: tifffile; extra == "docs"
